duckquest/__init__.py
duckquest/game_manager.py
duckquest/main.py
duckquest/assets/images/game_interface.png
duckquest/assets/images/logo.png
duckquest/assets/images/sample_graph.png
duckquest/assets/sounds/buzzer.wav
duckquest/assets/sounds/congratulation.wav
duckquest/assets/sounds/music_1.wav
duckquest/audio/__init__.py
duckquest/audio/manager.py
duckquest/data/rules.json
duckquest/graph/__init__.py
duckquest/graph/logic.py
duckquest/graph/manager.py
duckquest/graph/renderer.py
duckquest/graph/ui.py
duckquest/hardware/__init__.py
duckquest/hardware/button_manager.py
duckquest/hardware/led_strip_manager.py
duckquest/hardware/mock.py
duckquest/utils/__init__.py
duckquest/utils/helpers.py
duckquest/utils/logger.py
duckquest-0.5.0.dist-info/licenses/LICENSE
scripts/__init__.py
scripts/button_checker.py
scripts/hardware_checker.py
scripts/led_strip_checker.py
tests/__init__.py
tests/conftest.py
tests/launch_ui.py
tests/test_graph_logic.py
tests/test_graph_manager.py
tests/manual/__init__.py
tests/manual/test_launch_ui.py
duckquest-0.5.0.dist-info/METADATA
duckquest-0.5.0.dist-info/WHEEL
duckquest-0.5.0.dist-info/entry_points.txt
duckquest-0.5.0.dist-info/top_level.txt
duckquest-0.5.0.dist-info/RECORD
