Metadata-Version: 2.4
Name: duckquest
Version: 0.5.0
Summary: An educational game on the Raspberry Pi that teaches children about graph algorithms — DuckQuest prototype
Home-page: https://github.com/LeoLeman555/Board_Game_DuckQuest
Author: Léo Leman
Author-email: leo.leman555@gmail.com
License: MIT
Classifier: Development Status :: 3 - Alpha
Classifier: Programming Language :: Python :: 3.11
Classifier: Programming Language :: Python :: 3.12
Classifier: License :: OSI Approved :: MIT License
Classifier: Operating System :: OS Independent
Classifier: Intended Audience :: Education
Classifier: Topic :: Education
Requires-Python: >=3.11
License-File: LICENSE
Requires-Dist: matplotlib~=3.10
Requires-Dist: networkx~=3.4
Requires-Dist: pygame~=2.6
Requires-Dist: RPi.GPIO==0.7.1; platform_machine == "armv7l"
Requires-Dist: rpi_ws281x==5.0.0; platform_machine == "armv7l"
Dynamic: license-file
